{
    "File name": "product.jpg",
    "Name of operation": "Manufacturing Hook",
    "Steps": [
        {
            "Step number": 1,
            "Action": "Analyze drawing",
            "Equipment": [
                "CAD software"
            ],
            "ISO": [
                "ISO 2768"
            ]
        },
        {
            "Step number": 2,
            "Action": "Cut material to desired length",
            "Equipment": [
                "Shears (guillotine, disc)"
            ],
            "ISO": [
                "ISO 16092-3"
            ]
        },
        {
            "Step number": 3,
            "Action": "Bend material to form hook shape",
            "Equipment": [
                "Bending machines"
            ],
            "ISO": [
                "ISO 16092-3"
            ]
        },
        {
            "Step number": 4,
            "Action": "Drill holes for additional features",
            "Equipment": [
                "Drilling machines"
            ],
            "ISO": [
                "ISO 230-1"
            ]
        },
        {
            "Step number": 5,
            "Action": "Ream holes to precise dimensions",
            "Equipment": [
                "Reaming machines"
            ],
            "ISO": [
                "ISO 230-1"
            ]
        },
        {
            "Step number": 6,
            "Action": "Deburr edges",
            "Equipment": [
                "Deburring machines"
            ],
            "ISO": [
                "ISO 15740"
            ]
        },
        {
            "Step number": 7,
            "Action": "Sanding surface for finish",
            "Equipment": [
                "Sand-blasting equipment"
            ],
            "ISO": [
                "ISO 15740"
            ]
        },
        {
            "Step number": 8,
            "Action": "Polish surface",
            "Equipment": [
                "Grinding machines"
            ],
            "ISO": [
                "ISO 230-1"
            ]
        },
        {
            "Step number": 9,
            "Action": "Heat treatment for strength",
            "Equipment": [
                "Heat treatment furnaces"
            ],
            "ISO": [
                "ISO 17226"
            ]
        },
        {
            "Step number": 10,
            "Action": "Quality inspection for dimensions",
            "Equipment": [
                "Vernier calipers",
                "Measurement equipment"
            ],
            "ISO": [
                "ISO 3611"
            ]
        },
        {
            "Step number": 11,
            "Action": "Surface coating for corrosion resistance",
            "Equipment": [
                "Coating equipment"
            ],
            "ISO": [
                "ISO 12100"
            ]
        },
        {
            "Step number": 12,
            "Action": "Packaging for shipment",
            "Equipment": [
                "Trolleys, containers, racks"
            ],
            "ISO": [
                "ISO 2855"
            ]
        }
    ]
}